{
  "Databases": {
    "DataBase": {
      "Tables": {
        "Table": [
          {
            "IndexFiles": null,
            "uniqueKeys": {
              "UniqueAttribute": "SpecName"
            },
            "Structure": null,
            "primaryKey": null
          },
          {
            "IndexFiles": null,
            "foreignKeys": {
              "references": {
                "refAttribute": "Specid",
                "refTable": "Specialization"
              },
              "fkAttribute": "Specid"
            },
            "Structure": null,
            "primaryKey": null
          }
        ]
      }
    }
  }
}